Workbook
Name Slicer_City: #N/A
Name Slicer_Months__Date: #N/A
Name Slicer_Salesman: #N/A

Sheet sales_raw
A1: Date | B1: Invoice | C1: Product | D1: Customer | E1: City | F1: Salesman | G1: Qty | H1: Price | I1: Total
A2: 45751 | B2: INV00106 | C2: Semen Mortar | D2: Toko Bangunan 39 | E2: Bogor | F2: Andi | G2: 10 | H2: 55000 | I2: 550000
A3: 45707 | B3: INV00277 | C3: Bata Ringan 10cm | D3: Toko Bangunan 27 | E3: Depok | F3: Rina | G3: 10 | H3: 75000 | I3: 750000
A4: 45837 | B4: INV00407 | C4: Panel Dinding | D4: Toko Bangunan 11 | E4: Depok | F4: Budi | G4: 10 | H4: 120000 | I4: 1200000
A5: 45779 | B5: INV00598 | C5: Bata Ringan 7.5cm | D5: Toko Bangunan 1 | E5: Semarang | F5: Agus | G5: 10 | H5: 65000 | I5: 650000
A6: 45765 | B6: INV01051 | C6: Bata Ringan 7.5cm | D6: Toko Bangunan 8 | E6: Surabaya | F6: Rina | G6: 10 | H6: 65000 | I6: 650000
A7: 46003 | B7: INV01156 | C7: Bata Ringan 7.5cm | D7: Toko Bangunan 12 | E7: Jakarta | F7: Budi | G7: 10 | H7: 65000 | I7: 650000
A8: 45991 | B8: INV00075 | C8: Bata Ringan 7.5cm | D8: Toko Bangunan 8 | E8: Surabaya | F8: Andi | G8: 11 | H8: 65000 | I8: 715000
A9: 45749 | B9: INV00313 | C9: Panel Dinding | D9: Toko Bangunan 21 | E9: Tangerang | F9: Budi | G9: 11 | H9: 120000 | I9: 1320000
A10: 45827 | B10: INV00531 | C10: Semen Mortar | D10: Toko Bangunan 22 | E10: Bekasi | F10: Agus | G10: 11 | H10: 55000 | I10: 605000
A11: 45764 | B11: INV00823 | C11: Panel Dinding | D11: Toko Bangunan 44 | E11: Semarang | F11: Andi | G11: 11 | H11: 120000 | I11: 1320000
A12: 45871 | B12: INV00923 | C12: Bata Ringan 10cm | D12: Toko Bangunan 39 | E12: Bogor | F12: Budi | G12: 11 | H12: 75000 | I12: 825000
A13: 45942 | B13: INV00082 | C13: Panel Dinding | D13: Toko Bangunan 14 | E13: Bekasi | F13: Rina | G13: 12 | H13: 120000 | I13: 1440000
... A1201: 45833 | B1201: INV00820 | C1201: Bata Ringan 7.5cm | D1201: Toko Bangunan 44 | E1201: Semarang | F1201: Rina | G1201: 200 | H1201: 65000 | I1201: 13000000

Sheet targets
A1: Month | B1: Salesman | C1: Target
A2: Jan | B2: Andi | C2: 489501094
A3: Jan | B3: Budi | C3: 586356936
A4: Jan | B4: Rina | C4: 433178231
A5: Jan | B5: Sari | C5: 362208760
A6: Jan | B6: Agus | C6: 441380318
A7: Feb | B7: Andi | C7: 555148440
A8: Feb | B8: Budi | C8: 391540199
A9: Feb | B9: Rina | C9: 573696549
A10: Feb | B10: Sari | C10: 313079705
A11: Feb | B11: Agus | C11: 369802602
A12: Mar | B12: Andi | C12: 456941698
A13: Mar | B13: Budi | C13: 317407707
... A61: Dec | B61: Agus | C61: 492394117

Sheet products
A1: ProductID | B1: ProductName | C1: Category | D1: Price
A2: P001 | B2: Bata Ringan 7.5cm | C2: Material | D2: 65000
A3: P002 | B3: Bata Ringan 10cm | C3: Material | D3: 75000
A4: P003 | B4: Semen Mortar | C4: Material | D4: 55000
A5: P004 | B5: Panel Dinding | C5: Material | D5: 120000

Sheet customers
A1: CustomerID | B1: CustomerName | C1: City | D1: Segment
A2: C001 | B2: Toko Bangunan 1 | C2: Semarang | D2: Retail
A3: C002 | B3: Toko Bangunan 2 | C3: Surabaya | D3: Project
A4: C003 | B4: Toko Bangunan 3 | C4: Jakarta | D4: Distributor
A5: C004 | B5: Toko Bangunan 4 | C5: Surabaya | D5: Distributor
A6: C005 | B6: Toko Bangunan 5 | C6: Semarang | D6: Project
A7: C006 | B7: Toko Bangunan 6 | C7: Bogor | D7: Retail
A8: C007 | B8: Toko Bangunan 7 | C8: Bandung | D8: Distributor
A9: C008 | B9: Toko Bangunan 8 | C9: Surabaya | D9: Distributor
A10: C009 | B10: Toko Bangunan 9 | C10: Depok | D10: Project
A11: C010 | B11: Toko Bangunan 10 | C11: Bandung | D11: Project
A12: C011 | B12: Toko Bangunan 11 | C12: Depok | D12: Retail
... A51: C050 | B51: Toko Bangunan 50 | C51: Semarang | D51: Retail

Sheet Data Olahan
A3: Row Labels | B3: Sum of Total
A4: 2025 | B4: 2062770000
A5: Jan | B5: 194220000
A6: Feb | B6: 128775000
A7: Mar | B7: 101630000
A8: Apr | B8: 178305000
A9: May | B9: 267675000
A10: Jun | B10: 206910000
A11: Jul | B11: 191425000
A12: Aug | B12: 183880000
A13: Sep | B13: 253445000
A14: Oct | B14: 71005000
A15: Nov | B15: 172350000
... A17: Grand Total | B17: 2062770000
A24: Row Labels | B24: Sum of Total
A25: Panel Dinding | B25: 866280000
A26: Bata Ringan 10cm | B26: 411600000
A27: Bata Ringan 7.5cm | B27: 409955000
A28: Semen Mortar | B28: 374935000
A29: Grand Total | B29: 2062770000
A41: Row Labels | B41: Sum of Total
A42: Surabaya | B42: 391445000
A43: Jakarta | B43: 321625000
A44: Bogor | B44: 319885000
A45: Depok | B45: 291895000
A46: Semarang | B46: 290595000
A47: Bandung | B47: 166625000
A48: Bekasi | B48: 143095000
A49: Tangerang | B49: 137605000
A50: Grand Total | B50: 2062770000
A57: Row Labels | B57: Sum of Total
A58: Andi | B58: 2062770000
A59: Grand Total | B59: 2062770000
N76: Month | O76: (All)
A78: Salesman | B78: Years | C78: Month | D78: Actual | F78: Salesman | G78: Years | H78: Month | I78: Actual | J78: Target | K78: Achievement | L78: Status | N78: Count of Salesman | O78: Column Labels
A79: Andi | B79: 2025 | C79: Jan | D79: 194220000 | F79: Budi | G79: 2025 | H79: May | I79: 249765000 | J79: {=INDEX(targets!C:C, MATCH(1, (targets!A:A='Data Olahan'!H107)*(targets!B:B=F79), 0 ) )} -> 323811309 | K79: =IFERROR(I79/J79,0) -> 0.77132884 | L79: =IF(K79>=1,"Achieved","Not Achieved") -> Not Achieved | N79: Row Labels | O79: Not Achieved | P79: Grand Total
A80: Andi | B80: 2025 | C80: Feb | D80: 128775000 | F80: Rina | G80: 2025 | H80: Jun | I80: 266845000 | J80: {=INDEX(targets!C:C, MATCH(1, (targets!A:A='Data Olahan'!H120)*(targets!B:B=F80), 0 ) )} -> 533058667 | K80: =IFERROR(I80/J80,0) -> 0.50059218 | L80: =IF(K80>=1,"Achieved","Not Achieved") -> Not Achieved | N80: Agus | O80: 12 | P80: 12
A81: Andi | B81: 2025 | C81: Mar | D81: 101630000 | F81: Budi | G81: 2025 | H81: Sep | I81: 211555000 | J81: {=INDEX(targets!C:C, MATCH(1, (targets!A:A='Data Olahan'!H111)*(targets!B:B=F81), 0 ) )} -> 397170179 | K81: =IFERROR(I81/J81,0) -> 0.5326558 | L81: =IF(K81>=1,"Achieved","Not Achieved") -> Not Achieved | N81: Andi | O81: 12 | P81: 12
A82: Andi | B82: 2025 | C82: Apr | D82: 178305000 | F82: Andi | G82: 2025 | H82: Sep | I82: 253445000 | J82: {=INDEX(targets!C:C, MATCH(1, (targets!A:A='Data Olahan'!H99)*(targets!B:B=F82), 0 ) )} -> 489501094 | K82: =IFERROR(I82/J82,0) -> 0.51776187 | L82: =IF(K82>=1,"Achieved","Not Achieved") -> Not Achieved | N82: Budi | O82: 12 | P82: 12
A83: Andi | B83: 2025 | C83: May | D83: 267675000 | F83: Budi | G83: 2025 | H83: Oct | I83: 210025000 | J83: {=INDEX(targets!C:C, MATCH(1, (targets!A:A='Data Olahan'!H112)*(targets!B:B=F83), 0 ) )} -> 586356936 | K83: =IFERROR(I83/J83,0) -> 0.35818626 | L83: =IF(K83>=1,"Achieved","Not Achieved") -> Not Achieved | N83: Rina | O83: 12 | P83: 12
A84: Andi | B84: 2025 | C84: Jun | D84: 206910000 | F84: Rina | G84: 2025 | H84: Jul | I84: 206945000 | J84: {=INDEX(targets!C:C, MATCH(1, (targets!A:A='Data Olahan'!H121)*(targets!B:B=F84), 0 ) )} -> 373180748 | K84: =IFERROR(I84/J84,0) -> 0.55454361 | L84: =IF(K84>=1,"Achieved","Not Achieved") -> Not Achieved | N84: Sari | O84: 12 | P84: 12
A85: Andi | B85: 2025 | C85: Jul | D85: 191425000 | F85: Agus | G85: 2025 | H85: May | I85: 182365000 | J85: {=INDEX(targets!C:C, MATCH(1, (targets!A:A='Data Olahan'!H83)*(targets!B:B=F85), 0 ) )} -> 414761700 | K85: =IFERROR(I85/J85,0) -> 0.43968621 | L85: =IF(K85>=1,"Achieved","Not Achieved") -> Not Achieved | N85: Grand Total | O85: 60 | P85: 60
A86: Andi | B86: 2025 | C86: Aug | D86: 183880000 | F86: Sari | G86: 2025 | H86: Oct | I86: 214270000 | J86: {=INDEX(targets!C:C, MATCH(1, (targets!A:A='Data Olahan'!H136)*(targets!B:B=F86), 0 ) )} -> 445304373 | K86: =IFERROR(I86/J86,0) -> 0.4811765 | L86: =IF(K86>=1,"Achieved","Not Achieved") -> Not Achieved
A87: Andi | B87: 2025 | C87: Sep | D87: 253445000 | F87: Andi | G87: 2025 | H87: May | I87: 267675000 | J87: {=INDEX(targets!C:C, MATCH(1, (targets!A:A='Data Olahan'!H95)*(targets!B:B=F87), 0 ) )} -> 555148440 | K87: =IFERROR(I87/J87,0) -> 0.48216834 | L87: =IF(K87>=1,"Achieved","Not Achieved") -> Not Achieved
A88: Andi | B88: 2025 | C88: Oct | D88: 71005000 | F88: Sari | G88: 2025 | H88: Dec | I88: 212735000 | J88: {=INDEX(targets!C:C, MATCH(1, (targets!A:A='Data Olahan'!H138)*(targets!B:B=F88), 0 ) )} -> 470253837 | K88: =IFERROR(I88/J88,0) -> 0.45238334 | L88: =IF(K88>=1,"Achieved","Not Achieved") -> Not Achieved
A89: Andi | B89: 2025 | C89: Nov | D89: 172350000 | F89: Budi | G89: 2025 | H89: Mar | I89: 170395000 | J89: {=INDEX(targets!C:C, MATCH(1, (targets!A:A='Data Olahan'!H105)*(targets!B:B=F89), 0 ) )} -> 581403803 | K89: =IFERROR(I89/J89,0) -> 0.29307514 | L89: =IF(K89>=1,"Achieved","Not Achieved") -> Not Achieved | N89: Row Labels | O89: Average of Achievement
A90: Andi | B90: 2025 | C90: Dec | D90: 113150000 | F90: Andi | G90: 2025 | H90: Jun | I90: 206910000 | J90: {=INDEX(targets!C:C, MATCH(1, (targets!A:A='Data Olahan'!H96)*(targets!B:B=F90), 0 ) )} -> 456941698 | K90: =IFERROR(I90/J90,0) -> 0.45281488 | L90: =IF(K90>=1,"Achieved","Not Achieved") -> Not Achieved | N90: Sari | O90: 0.45677675
A91: Andi Total | D91: 2062770000 | F91: Sari | G91: 2025 | H91: Jul | I91: 209330000 | J91: {=INDEX(targets!C:C, MATCH(1, (targets!A:A='Data Olahan'!H133)*(targets!B:B=F91), 0 ) )} -> 497321332 | K91: =IFERROR(I91/J91,0) -> 0.42091498 | L91: =IF(K91>=1,"Achieved","Not Achieved") -> Not Achieved | N91: Budi | O91: 0.39727791
A92: Grand Total | D92: 2062770000 | F92: Sari | G92: 2025 | H92: Sep | I92: 195540000 | J92: {=INDEX(targets!C:C, MATCH(1, (targets!A:A='Data Olahan'!H135)*(targets!B:B=F92), 0 ) )} -> 350125110 | K92: =IFERROR(I92/J92,0) -> 0.55848608 | L92: =IF(K92>=1,"Achieved","Not Achieved") -> Not Achieved | N92: Rina | O92: 0.38930815
F93: Sari | G93: 2025 | H93: Nov | I93: 175595000 | J93: {=INDEX(targets!C:C, MATCH(1, (targets!A:A='Data Olahan'!H137)*(targets!B:B=F93), 0 ) )} -> 322869545 | K93: =IFERROR(I93/J93,0) -> 0.54385743 | L93: =IF(K93>=1,"Achieved","Not Achieved") -> Not Achieved | N93: Andi | O93: 0.35685703
F94: Budi | G94: 2025 | H94: Feb | I94: 175955000 | J94: {=INDEX(targets!C:C, MATCH(1, (targets!A:A='Data Olahan'!H104)*(targets!B:B=F94), 0 ) )} -> 323811309 | K94: =IFERROR(I94/J94,0) -> 0.54338745 | L94: =IF(K94>=1,"Achieved","Not Achieved") -> Not Achieved | N94: Agus | O94: 0.29891724
F95: Rina | G95: 2025 | H95: Feb | I95: 189475000 | J95: {=INDEX(targets!C:C, MATCH(1, (targets!A:A='Data Olahan'!H116)*(targets!B:B=F95), 0 ) )} -> 426869098 | K95: =IFERROR(I95/J95,0) -> 0.44387144 | L95: =IF(K95>=1,"Achieved","Not Achieved") -> Not Achieved | N95: Grand Total | O95: 0.37982741
F96: Sari | G96: 2025 | H96: Mar | I96: 172980000 | J96: {=INDEX(targets!C:C, MATCH(1, (targets!A:A='Data Olahan'!H129)*(targets!B:B=F96), 0 ) )} -> 313079705 | K96: =IFERROR(I96/J96,0) -> 0.55251106 | L96: =IF(K96>=1,"Achieved","Not Achieved") -> Not Achieved
F97: Agus | G97: 2025 | H97: Oct | I97: 147310000 | J97: {=INDEX(targets!C:C, MATCH(1, (targets!A:A='Data Olahan'!H88)*(targets!B:B=F97), 0 ) )} -> 492394117 | K97: =IFERROR(I97/J97,0) -> 0.29917092 | L97: =IF(K97>=1,"Achieved","Not Achieved") -> Not Achieved
F98: Andi | G98: 2025 | H98: Jul | I98: 191425000 | J98: {=INDEX(targets!C:C, MATCH(1, (targets!A:A='Data Olahan'!H97)*(targets!B:B=F98), 0 ) )} -> 450598722 | K98: =IFERROR(I98/J98,0) -> 0.42482366 | L98: =IF(K98>=1,"Achieved","Not Achieved") -> Not Achieved
F99: Sari | G99: 2025 | H99: Jan | I99: 171660000 | J99: {=INDEX(targets!C:C, MATCH(1, (targets!A:A='Data Olahan'!H127)*(targets!B:B=F99), 0 ) )} -> 313079705 | K99: =IFERROR(I99/J99,0) -> 0.54829488 | L99: =IF(K99>=1,"Achieved","Not Achieved") -> Not Achieved
F100: Rina | G100: 2025 | H100: Jan | I100: 150835000 | J100: {=INDEX(targets!C:C, MATCH(1, (targets!A:A='Data Olahan'!H115)*(targets!B:B=F100), 0 ) )} -> 327980786 | K100: =IFERROR(I100/J100,0) -> 0.45988974 | L100: =IF(K100>=1,"Achieved","Not Achieved") -> Not Achieved
F101: Andi | G101: 2025 | H101: Aug | I101: 183880000 | J101: {=INDEX(targets!C:C, MATCH(1, (targets!A:A='Data Olahan'!H98)*(targets!B:B=F101), 0 ) )} -> 477049986 | K101: =IFERROR(I101/J101,0) -> 0.38545227 | L101: =IF(K101>=1,"Achieved","Not Achieved") -> Not Achieved | N101: Salesman | O101: Month | P101: Sum of Actual | Q101: Sum of Target
F102: Budi | G102: 2025 | H102: Jan | I102: 234810000 | J102: {=INDEX(targets!C:C, MATCH(1, (targets!A:A='Data Olahan'!H103)*(targets!B:B=F102), 0 ) )} -> 586356936 | K102: =IFERROR(I102/J102,0) -> 0.40045574 | L102: =IF(K102>=1,"Achieved","Not Achieved") -> Not Achieved | N102: Agus | O102: Jan | P102: 148270000 | Q102: 494429768
F103: Andi | G103: 2025 | H103: Jan | I103: 194220000 | J103: {=INDEX(targets!C:C, MATCH(1, (targets!A:A='Data Olahan'!H91)*(targets!B:B=F103), 0 ) )} -> 477049986 | K103: =IFERROR(I103/J103,0) -> 0.40712715 | L103: =IF(K103>=1,"Achieved","Not Achieved") -> Not Achieved | O103: Feb | P103: 114450000 | Q103: 438202318
F104: Rina | G104: 2025 | H104: Aug | I104: 191045000 | J104: {=INDEX(targets!C:C, MATCH(1, (targets!A:A='Data Olahan'!H122)*(targets!B:B=F104), 0 ) )} -> 445738123 | K104: =IFERROR(I104/J104,0) -> 0.42860368 | L104: =IF(K104>=1,"Achieved","Not Achieved") -> Not Achieved | O104: Mar | P104: 110750000 | Q104: 534429847
F105: Andi | G105: 2025 | H105: Apr | I105: 178305000 | J105: {=INDEX(targets!C:C, MATCH(1, (targets!A:A='Data Olahan'!H94)*(targets!B:B=F105), 0 ) )} -> 555148440 | K105: =IFERROR(I105/J105,0) -> 0.32118437 | L105: =IF(K105>=1,"Achieved","Not Achieved") -> Not Achieved | O105: Apr | P105: 179705000 | Q105: 534429847
F106: Rina | G106: 2025 | H106: Nov | I106: 168265000 | J106: {=INDEX(targets!C:C, MATCH(1, (targets!A:A='Data Olahan'!H125)*(targets!B:B=F106), 0 ) )} -> 377540700 | K106: =IFERROR(I106/J106,0) -> 0.44568705 | L106: =IF(K106>=1,"Achieved","Not Achieved") -> Not Achieved | O106: May | P106: 182365000 | Q106: 414761700
F107: Sari | G107: 2025 | H107: Aug | I107: 171540000 | J107: {=INDEX(targets!C:C, MATCH(1, (targets!A:A='Data Olahan'!H134)*(targets!B:B=F107), 0 ) )} -> 354735349 | K107: =IFERROR(I107/J107,0) -> 0.48357177 | L107: =IF(K107>=1,"Achieved","Not Achieved") -> Not Achieved | O107: Jun | P107: 131350000 | Q107: 516629413
F108: Budi | G108: 2025 | H108: Jul | I108: 209955000 | J108: {=INDEX(targets!C:C, MATCH(1, (targets!A:A='Data Olahan'!H109)*(targets!B:B=F108), 0 ) )} -> 556351160 | K108: =IFERROR(I108/J108,0) -> 0.37737856 | L108: =IF(K108>=1,"Achieved","Not Achieved") -> Not Achieved | O108: Jul | P108: 177560000 | Q108: 494429768
F109: Agus | G109: 2025 | H109: Jun | I109: 131350000 | J109: {=INDEX(targets!C:C, MATCH(1, (targets!A:A='Data Olahan'!H84)*(targets!B:B=F109), 0 ) )} -> 516629413 | K109: =IFERROR(I109/J109,0) -> 0.25424414 | L109: =IF(K109>=1,"Achieved","Not Achieved") -> Not Achieved | O109: Aug | P109: 66890000 | Q109: 492394117
F110: Agus | G110: 2025 | H110: Apr | I110: 179705000 | J110: {=INDEX(targets!C:C, MATCH(1, (targets!A:A='Data Olahan'!H82)*(targets!B:B=F110), 0 ) )} -> 534429847 | K110: =IFERROR(I110/J110,0) -> 0.33625555 | L110: =IF(K110>=1,"Achieved","Not Achieved") -> Not Achieved | O110: Sep | P110: 105470000 | Q110: 494429768
F111: Agus | G111: 2025 | H111: Dec | I111: 176845000 | J111: {=INDEX(targets!C:C, MATCH(1, (targets!A:A='Data Olahan'!H90)*(targets!B:B=F111), 0 ) )} -> 438202318 | K111: =IFERROR(I111/J111,0) -> 0.40356929 | L111: =IF(K111>=1,"Achieved","Not Achieved") -> Not Achieved | O111: Oct | P111: 147310000 | Q111: 441380318
F112: Agus | G112: 2025 | H112: Jan | I112: 148270000 | J112: {=INDEX(targets!C:C, MATCH(1, (targets!A:A='Data Olahan'!H79)*(targets!B:B=F112), 0 ) )} -> 494429768 | K112: =IFERROR(I112/J112,0) -> 0.29988081 | L112: =IF(K112>=1,"Achieved","Not Achieved") -> Not Achieved | O112: Nov | P112: 129000000 | Q112: 376172492
F113: Sari | G113: 2025 | H113: Jun | I113: 163760000 | J113: {=INDEX(targets!C:C, MATCH(1, (targets!A:A='Data Olahan'!H132)*(targets!B:B=F113), 0 ) )} -> 350125110 | K113: =IFERROR(I113/J113,0) -> 0.46771852 | L113: =IF(K113>=1,"Achieved","Not Achieved") -> Not Achieved | O113: Dec | P113: 176845000 | Q113: 438202318
F114: Sari | G114: 2025 | H114: Feb | I114: 156230000 | J114: {=INDEX(targets!C:C, MATCH(1, (targets!A:A='Data Olahan'!H128)*(targets!B:B=F114), 0 ) )} -> 350125110 | K114: =IFERROR(I114/J114,0) -> 0.44621193 | L114: =IF(K114>=1,"Achieved","Not Achieved") -> Not Achieved | N114: Agus Total | P114: 1669965000 | Q114: 5669891674
F115: Rina | G115: 2025 | H115: Oct | I115: 149015000 | J115: {=INDEX(targets!C:C, MATCH(1, (targets!A:A='Data Olahan'!H124)*(targets!B:B=F115), 0 ) )} -> 373180748 | K115: =IFERROR(I115/J115,0) -> 0.39931052 | L115: =IF(K115>=1,"Achieved","Not Achieved") -> Not Achieved | N115: Andi | O115: Jan | P115: 194220000 | Q115: 555148440
F116: Agus | G116: 2025 | H116: Jul | I116: 177560000 | J116: {=INDEX(targets!C:C, MATCH(1, (targets!A:A='Data Olahan'!H85)*(targets!B:B=F116), 0 ) )} -> 494429768 | K116: =IFERROR(I116/J116,0) -> 0.35912077 | L116: =IF(K116>=1,"Achieved","Not Achieved") -> Not Achieved | O116: Feb | P116: 128775000 | Q116: 512756543
F117: Budi | G117: 2025 | H117: Aug | I117: 129575000 | J117: {=INDEX(targets!C:C, MATCH(1, (targets!A:A='Data Olahan'!H110)*(targets!B:B=F117), 0 ) )} -> 581403803 | K117: =IFERROR(I117/J117,0) -> 0.22286576 | L117: =IF(K117>=1,"Achieved","Not Achieved") -> Not Achieved | O117: Mar | P117: 101630000 | Q117: 456018469
F118: Andi | G118: 2025 | H118: Nov | I118: 172350000 | J118: {=INDEX(targets!C:C, MATCH(1, (targets!A:A='Data Olahan'!H101)*(targets!B:B=F118), 0 ) )} -> 512756543 | K118: =IFERROR(I118/J118,0) -> 0.33612443 | L118: =IF(K118>=1,"Achieved","Not Achieved") -> Not Achieved | O118: Apr | P118: 178305000 | Q118: 555148440
F119: Budi | G119: 2025 | H119: Apr | I119: 171145000 | J119: {=INDEX(targets!C:C, MATCH(1, (targets!A:A='Data Olahan'!H106)*(targets!B:B=F119), 0 ) )} -> 313993616 | K119: =IFERROR(I119/J119,0) -> 0.54505885 | L119: =IF(K119>=1,"Achieved","Not Achieved") -> Not Achieved | O119: May | P119: 267675000 | Q119: 555148440
F120: Rina | G120: 2025 | H120: Dec | I120: 148615000 | J120: {=INDEX(targets!C:C, MATCH(1, (targets!A:A='Data Olahan'!H126)*(targets!B:B=F120), 0 ) )} -> 533058667 | K120: =IFERROR(I120/J120,0) -> 0.27879671 | L120: =IF(K120>=1,"Achieved","Not Achieved") -> Not Achieved | O120: Jun | P120: 206910000 | Q120: 477049986
F121: Budi | G121: 2025 | H121: Nov | I121: 95485000 | J121: {=INDEX(targets!C:C, MATCH(1, (targets!A:A='Data Olahan'!H113)*(targets!B:B=F121), 0 ) )} -> 556351160 | K121: =IFERROR(I121/J121,0) -> 0.17162721 | L121: =IF(K121>=1,"Achieved","Not Achieved") -> Not Achieved | O121: Jul | P121: 191425000 | Q121: 450598722
F122: Rina | G122: 2025 | H122: Sep | I122: 150905000 | J122: {=INDEX(targets!C:C, MATCH(1, (targets!A:A='Data Olahan'!H123)*(targets!B:B=F122), 0 ) )} -> 445738123 | K122: =IFERROR(I122/J122,0) -> 0.3385508 | L122: =IF(K122>=1,"Achieved","Not Achieved") -> Not Achieved | O122: Aug | P122: 183880000 | Q122: 477049986
F123: Agus | G123: 2025 | H123: Sep | I123: 105470000 | J123: {=INDEX(targets!C:C, MATCH(1, (targets!A:A='Data Olahan'!H87)*(targets!B:B=F123), 0 ) )} -> 494429768 | K123: =IFERROR(I123/J123,0) -> 0.21331644 | L123: =IF(K123>=1,"Achieved","Not Achieved") -> Not Achieved | O123: Sep | P123: 253445000 | Q123: 362719821
F124: Agus | G124: 2025 | H124: Nov | I124: 129000000 | J124: {=INDEX(targets!C:C, MATCH(1, (targets!A:A='Data Olahan'!H89)*(targets!B:B=F124), 0 ) )} -> 376172492 | K124: =IFERROR(I124/J124,0) -> 0.34292779 | L124: =IF(K124>=1,"Achieved","Not Achieved") -> Not Achieved | O124: Oct | P124: 71005000 | Q124: 489501094
F125: Rina | G125: 2025 | H125: May | I125: 101955000 | J125: {=INDEX(targets!C:C, MATCH(1, (targets!A:A='Data Olahan'!H119)*(targets!B:B=F125), 0 ) )} -> 481011760 | K125: =IFERROR(I125/J125,0) -> 0.21195947 | L125: =IF(K125>=1,"Achieved","Not Achieved") -> Not Achieved | O125: Nov | P125: 172350000 | Q125: 512756543
F126: Budi | G126: 2025 | H126: Dec | I126: 158010000 | J126: {=INDEX(targets!C:C, MATCH(1, (targets!A:A='Data Olahan'!H114)*(targets!B:B=F126), 0 ) )} -> 391540199 | K126: =IFERROR(I126/J126,0) -> 0.4035601 | L126: =IF(K126>=1,"Achieved","Not Achieved") -> Not Achieved | O126: Dec | P126: 113150000 | Q126: 489501094
F127: Andi | G127: 2025 | H127: Feb | I127: 128775000 | J127: {=INDEX(targets!C:C, MATCH(1, (targets!A:A='Data Olahan'!H92)*(targets!B:B=F127), 0 ) )} -> 362719821 | K127: =IFERROR(I127/J127,0) -> 0.35502609 | L127: =IF(K127>=1,"Achieved","Not Achieved") -> Not Achieved | N127: Andi Total | P127: 2062770000 | Q127: 5893397578
F128: Agus | G128: 2025 | H128: Mar | I128: 110750000 | J128: {=INDEX(targets!C:C, MATCH(1, (targets!A:A='Data Olahan'!H81)*(targets!B:B=F128), 0 ) )} -> 534429847 | K128: =IFERROR(I128/J128,0) -> 0.20723019 | L128: =IF(K128>=1,"Achieved","Not Achieved") -> Not Achieved | N128: Budi | O128: Jan | P128: 234810000 | Q128: 586356936
F129: Agus | G129: 2025 | H129: Feb | I129: 114450000 | J129: {=INDEX(targets!C:C, MATCH(1, (targets!A:A='Data Olahan'!H80)*(targets!B:B=F129), 0 ) )} -> 438202318 | K129: =IFERROR(I129/J129,0) -> 0.26118073 | L129: =IF(K129>=1,"Achieved","Not Achieved") -> Not Achieved | O129: Feb | P129: 175955000 | Q129: 323811309
F130: Rina | G130: 2025 | H130: Apr | I130: 100685000 | J130: {=INDEX(targets!C:C, MATCH(1, (targets!A:A='Data Olahan'!H118)*(targets!B:B=F130), 0 ) )} -> 373180748 | K130: =IFERROR(I130/J130,0) -> 0.26980224 | L130: =IF(K130>=1,"Achieved","Not Achieved") -> Not Achieved | O130: Mar | P130: 170395000 | Q130: 581403803
F131: Sari | G131: 2025 | H131: May | I131: 92620000 | J131: {=INDEX(targets!C:C, MATCH(1, (targets!A:A='Data Olahan'!H131)*(targets!B:B=F131), 0 ) )} -> 347981463 | K131: =IFERROR(I131/J131,0) -> 0.2661636 | L131: =IF(K131>=1,"Achieved","Not Achieved") -> Not Achieved | O131: Apr | P131: 171145000 | Q131: 313993616
F132: Andi | G132: 2025 | H132: Mar | I132: 101630000 | J132: {=INDEX(targets!C:C, MATCH(1, (targets!A:A='Data Olahan'!H93)*(targets!B:B=F132), 0 ) )} -> 391633543 | K132: =IFERROR(I132/J132,0) -> 0.2595028 | L132: =IF(K132>=1,"Achieved","Not Achieved") -> Not Achieved | O132: May | P132: 249765000 | Q132: 497707145
F133: Andi | G133: 2025 | H133: Dec | I133: 113150000 | J133: {=INDEX(targets!C:C, MATCH(1, (targets!A:A='Data Olahan'!H102)*(targets!B:B=F133), 0 ) )} -> 489501094 | K133: =IFERROR(I133/J133,0) -> 0.23115372 | L133: =IF(K133>=1,"Achieved","Not Achieved") -> Not Achieved | O133: Jun | P133: 105900000 | Q133: 555825106
F134: Budi | G134: 2025 | H134: Jun | I134: 105900000 | J134: {=INDEX(targets!C:C, MATCH(1, (targets!A:A='Data Olahan'!H108)*(targets!B:B=F134), 0 ) )} -> 555825106 | K134: =IFERROR(I134/J134,0) -> 0.19052756 | L134: =IF(K134>=1,"Achieved","Not Achieved") -> Not Achieved | O134: Jul | P134: 209955000 | Q134: 556351160
F135: Rina | G135: 2025 | H135: Mar | I135: 104315000 | J135: {=INDEX(targets!C:C, MATCH(1, (targets!A:A='Data Olahan'!H117)*(targets!B:B=F135), 0 ) )} -> 306727352 | K135: =IFERROR(I135/J135,0) -> 0.34009031 | L135: =IF(K135>=1,"Achieved","Not Achieved") -> Not Achieved | O135: Aug | P135: 129575000 | Q135: 581403803
F136: Sari | G136: 2025 | H136: Apr | I136: 81770000 | J136: {=INDEX(targets!C:C, MATCH(1, (targets!A:A='Data Olahan'!H130)*(targets!B:B=F136), 0 ) )} -> 445304373 | K136: =IFERROR(I136/J136,0) -> 0.18362721 | L136: =IF(K136>=1,"Achieved","Not Achieved") -> Not Achieved | O136: Sep | P136: 211555000 | Q136: 397170179
F137: Agus | G137: 2025 | H137: Aug | I137: 66890000 | J137: {=INDEX(targets!C:C, MATCH(1, (targets!A:A='Data Olahan'!H86)*(targets!B:B=F137), 0 ) )} -> 414761700 | K137: =IFERROR(I137/J137,0) -> 0.16127333 | L137: =IF(K137>=1,"Achieved","Not Achieved") -> Not Achieved | O137: Oct | P137: 210025000 | Q137: 586356936
F138: Andi | G138: 2025 | H138: Oct | I138: 71005000 | J138: {=INDEX(targets!C:C, MATCH(1, (targets!A:A='Data Olahan'!H100)*(targets!B:B=F138), 0 ) )} -> 489501094 | K138: =IFERROR(I138/J138,0) -> 0.14505586 | L138: =IF(K138>=1,"Achieved","Not Achieved") -> Not Achieved | O138: Nov | P138: 95485000 | Q138: 313993616
O139: Dec | P139: 158010000 | Q139: 317407707
N140: Budi Total | P140: 2122575000 | Q140: 5611781316
N141: Rina | O141: Jan | P141: 150835000 | Q141: 327980786
O142: Feb | P142: 189475000 | Q142: 426869098
O143: Mar | P143: 104315000 | Q143: 306727352
...

Sheet Data Mentah Forecast
A1: Jan | B1: 899795000 | C1: =DATE(2025, ROW(A1), 1) -> 45658
A2: Feb | B2: 764885000 | C2: =DATE(2025, ROW(A2), 1) -> 45689
A3: Mar | B3: 660070000 | C3: =DATE(2025, ROW(A3), 1) -> 45717
A4: Apr | B4: 711610000 | C4: =DATE(2025, ROW(A4), 1) -> 45748
A5: May | B5: 894380000 | C5: =DATE(2025, ROW(A5), 1) -> 45778
A6: Jun | B6: 874765000 | C6: =DATE(2025, ROW(A6), 1) -> 45809
A7: Jul | B7: 995215000 | C7: =DATE(2025, ROW(A7), 1) -> 45839
A8: Aug | B8: 742930000 | C8: =DATE(2025, ROW(A8), 1) -> 45870
A9: Sep | B9: 916915000 | C9: =DATE(2025, ROW(A9), 1) -> 45901
A10: Oct | B10: 791625000 | C10: =DATE(2025, ROW(A10), 1) -> 45931
A11: Nov | B11: 740695000 | C11: =DATE(2025, ROW(A11), 1) -> 45962
A12: Dec | B12: 809355000 | C12: =DATE(2025, ROW(A12), 1) -> 45992

Sheet Forecast 
A1: Timeline | B1: Values | C1: Forecast | D1: Lower Confidence Bound | E1: Upper Confidence Bound
A2: 45658 | B2: 899795000
A3: 45689 | B3: 764885000
A4: 45717 | B4: 660070000
A5: 45748 | B5: 711610000
A6: 45778 | B6: 894380000
A7: 45809 | B7: 874765000
A8: 45839 | B8: 995215000
A9: 45870 | B9: 742930000
A10: 45901 | B10: 916915000
A11: 45931 | B11: 791625000
A12: 45962 | B12: 740695000
A13: 45992 | B13: 809355000 | C13: 809355000 | D13: 809355000 | E13: 809355000
A14: 46023 | C14: =_xlfn.FORECAST.ETS(A14,$B$2:$B$13,$A$2:$A$13,1,1) -> 8.1905784e+08 | D14: =C14-_xlfn.FORECAST.ETS.CONFINT(A14,$B$2:$B$13,$A$2:$A$13,0.95,1,1) -> 5.9830595e+08 | E14: =C14+_xlfn.FORECAST.ETS.CONFINT(A14,$B$2:$B$13,$A$2:$A$13,0.95,1,1) -> 1.0398097e+09
A15: 46054 | C15: =_xlfn.FORECAST.ETS(A15,$B$2:$B$13,$A$2:$A$13,1,1) -> 8.2008218e+08 | D15: =C15-_xlfn.FORECAST.ETS.CONFINT(A15,$B$2:$B$13,$A$2:$A$13,0.95,1,1) -> 5.924827e+08 | E15: =C15+_xlfn.FORECAST.ETS.CONFINT(A15,$B$2:$B$13,$A$2:$A$13,0.95,1,1) -> 1.0476817e+09
A16: 46082 | C16: =_xlfn.FORECAST.ETS(A16,$B$2:$B$13,$A$2:$A$13,1,1) -> 8.2110652e+08 | D16: =C16-_xlfn.FORECAST.ETS.CONFINT(A16,$B$2:$B$13,$A$2:$A$13,0.95,1,1) -> 5.8680722e+08 | E16: =C16+_xlfn.FORECAST.ETS.CONFINT(A16,$B$2:$B$13,$A$2:$A$13,0.95,1,1) -> 1.0554058e+09
A17: 46112 | C17: =_xlfn.FORECAST.ETS(A17,$B$2:$B$13,$A$2:$A$13,1,1) -> 8.2209782e+08 | D17: =C17-_xlfn.FORECAST.ETS.CONFINT(A17,$B$2:$B$13,$A$2:$A$13,0.95,1,1) -> 5.8144291e+08 | E17: =C17+_xlfn.FORECAST.ETS.CONFINT(A17,$B$2:$B$13,$A$2:$A$13,0.95,1,1) -> 1.0627527e+09

Sheet Dashboard Performa Sales
A6: Total Sales
A7: =GETPIVOTDATA("Total",'Data Olahan'!$A$266) -> 2062770000
A16: Total Quantity
A17: =GETPIVOTDATA("Qty",'Data Olahan'!$D$266) -> 25831
A25: Total Customer
A26: =GETPIVOTDATA("[Measures].[Distinct Count of Customer]",'Data Olahan'!$A$289) -> 50
A33: Target Achievement
A34: =GETPIVOTDATA("Achievement",'Data Olahan'!$D$289) -> 0.37982741
P50: Row Labels | Q50: Average of Achievement
P51: Sari | Q51: 0.45677675
P52: Budi | Q52: 0.39727791
P53: Rina | Q53: 0.38930815
P54: Andi | Q54: 0.35685703
P55: Agus | Q55: 0.29891724
P56: Grand Total | Q56: 0.37982741
O78: Timeline | P78: Values | Q78: Forecast | R78: Lower Confidence Bound | S78: Upper Confidence Bound
O79: 45658 | P79: 899795000
O80: 45689 | P80: 764885000
O81: 45717 | P81: 660070000
O82: 45748 | P82: 711610000
O83: 45778 | P83: 894380000
O84: 45809 | P84: 874765000
O85: 45839 | P85: 995215000
O86: 45870 | P86: 742930000
O87: 45901 | P87: 916915000
O88: 45931 | P88: 791625000
O89: 45962 | P89: 740695000
O90: 45992 | P90: 809355000 | Q90: 809355000 | R90: 809355000 | S90: 809355000
O91: 46023 | Q91: 8.1905784e+08 | R91: 5.9830595e+08 | S91: 1.0398097e+09
O92: 46054 | Q92: 8.2008218e+08 | R92: 5.924827e+08 | S92: 1.0476817e+09
O93: 46082 | Q93: 8.2110652e+08 | R93: 5.8680722e+08 | S93: 1.0554058e+09
O94: 46112 | Q94: 8.2209782e+08 | R94: 5.8144291e+08 | S94: 1.0627527e+09
